odoo/addons/rental_offday/README.rst
odoo/addons/rental_offday/__init__.py
odoo/addons/rental_offday/__manifest__.py
odoo/addons/rental_offday/README/CONTRIBUTORS.rst
odoo/addons/rental_offday/README/DESCRIPTION.rst
odoo/addons/rental_offday/README/HISTORY.rst
odoo/addons/rental_offday/README/USAGE.rst
odoo/addons/rental_offday/i18n/de.po
odoo/addons/rental_offday/i18n/it.po
odoo/addons/rental_offday/i18n/rental_offday.pot
odoo/addons/rental_offday/models/__init__.py
odoo/addons/rental_offday/models/rental_offday.py
odoo/addons/rental_offday/models/sale.py
odoo/addons/rental_offday/security/ir.model.access.csv
odoo/addons/rental_offday/static/description/icon.png
odoo/addons/rental_offday/static/description/index.html
odoo/addons/rental_offday/tests/__init__.py
odoo/addons/rental_offday/tests/test_rental_offday.py
odoo/addons/rental_offday/views/sale_view.xml
odoo14_addon_rental_offday-14.0.1.0.1.dev7.dist-info/METADATA
odoo14_addon_rental_offday-14.0.1.0.1.dev7.dist-info/WHEEL
odoo14_addon_rental_offday-14.0.1.0.1.dev7.dist-info/top_level.txt
odoo14_addon_rental_offday-14.0.1.0.1.dev7.dist-info/RECORD
