Metadata-Version: 2.1
Name: odoo14-addon-rental_offday
Version: 14.0.1.0.1.dev7
Summary: Manage off-days in rentals on daily basis
Home-page: https://github.com/OCA/vertical-rental
Author: elego Software Solutions GmbH, Odoo Community Association (OCA)
Author-email: support@odoo-community.org
License: AGPL-3
Classifier: Programming Language :: Python
Classifier: Framework :: Odoo
Classifier: Framework :: Odoo :: 14.0
Classifier: License :: OSI Approved :: GNU Affero General Public License v3
Requires-Python: >=3.6
Requires-Dist: odoo14-addon-rental-pricelist
Requires-Dist: odoo<14.1dev,>=14.0a
